Workbook

Sheet Consumer ROI Dashboard
A1: Smart HVAC Controller: Consumer ROI and Payback Dashboard
A3: Key Consumer Result | B3: Value | C3: Interpretation
A4: Total Consumer CAPEX | B4: ='Consumer Inputs'!B11+'Consumer Inputs'!B12+'Consumer Inputs'!B16 -> 26000 | C4: Product package + installation/setup + financing cost.
A5: Year 1 Manual HVAC Bill | B5: ='Consumer Cash Flow'!F5 -> 23753.155 | C5: Cost of existing HVAC operation before smart controller.
A6: Year 1 Smart HVAC Bill | B6: ='Consumer Cash Flow'!G5 -> 18874.352 | C6: Cost after the controller reduces HVAC energy consumption.
A7: Year 1 kWh Saved | B7: ='Consumer Cash Flow'!E5 -> 464.43117 | C7: Energy reduction achieved by controller operation.
A8: Year 1 Gross Electricity Savings | B8: ='Consumer Cash Flow'!F5-'Consumer Cash Flow'!G5 -> 4878.8029 | C8: Bill reduction before annual controller OPEX.
A9: Annual Smart Controller OPEX | B9: ='Consumer Inputs'!B13 -> 1389.4 | C9: Recurring cloud/maintenance/subscription cost.
A10: Year 1 Net Savings | B10: ='Consumer Cash Flow'!I5 -> 3489.4029 | C10: Gross electricity savings minus controller OPEX plus optional maintenance savings.
A11: Simple Payback Period | B11: =IF(B9>0,B4/B9,"Not recovered") -> 18.713114 | C11: Years needed for the consumer to recover initial investment.
A12: Discounted Payback Year | B12: =IFERROR(INDEX('Consumer Cash Flow'!A5:A14,MATCH(TRUE,'Consumer Cash Flow'!K5:K14>=0,0)),"Not recovered") -> Not recovered | C12: First year when discounted cumulative cash flow becomes positive.
A13: 3-Year ROI | B13: =IF(B4>0,(SUM('Consumer Cash Flow'!I5:I7)+'Consumer Inputs'!B15-B4)/B4,0) -> -0.53209459 | C13: Consumer return over 3 years based on net cash savings.
A14: 5-Year ROI | B14: =IF(B4>0,(SUM('Consumer Cash Flow'!I5:I9)+'Consumer Inputs'!B15-B4)/B4,0) -> -0.094377672 | C14: Consumer return over 5 years based on net cash savings.
A15: 10-Year ROI | B15: =IF(B4>0,(SUM('Consumer Cash Flow'!I5:I14)+'Consumer Inputs'!B15-B4)/B4,0) -> 1.6307667 | C15: Consumer return over 10 years based on net cash savings.
A16: NPV of Consumer Savings | B16: =SUM('Consumer Cash Flow'!J4:J14) -> -2290.7453 | C16: Present value of all net cash flows including initial CAPEX.
A17: Controller Depreciation / Year | B17: ='Depreciation Schedule'!B5 -> 2166.6667 | C17: Straight-line accounting depreciation; not a cash expense.

Sheet Consumer Inputs
A1: Smart HVAC Controller Consumer-Side Assumptions
A3: Input | B3: Value | C3: Unit | D3: Purpose / Meanimgng
A4: Analysis Horizon | B4: 12 | C4: years | D4: Consumer ownership period used for ROI and payback evaluation.
A5: Electricity Rate | B5: 10.5049 | C5: Peso/kWh | D5: Consumer tariff paid for HVAC electricity consumption in Year 1.
A6: Electricity Rate Escalation | B6: 0.09 | C6: %/year | D6: Expected yearly increase in electricity price.
A7: Optional Discount Rate | B7: 0.2 | C7: %/year | D7: Used only for discounted payback and present-value savings.
A8: Existing HVAC Annual Energy Consumption (Before Smart Controller) | B8: 2261.15 | C8: kWh/year | D8: Measured or estimated Year 1 annual HVAC energy consumption under manual setpoint operation. The HVAC unit is not purchased; it already exists.
A9: Annual HVAC Energy Consumption Variation | B9: 0.02 | C9: %/year | D9: Expected yearly change in existing HVAC energy use due to weather, occupancy, operating hours, and equipment aging.
A10: Measured Energy Savings Achieved by Smart HVAC Controller | B10: 0.205396 | C10: % | D10: Experimentally observed savings delivered by the controller; applied to each year's projected baseline HVAC consumption.
A11: Smart HVAC Controller Package Cost | B11: 26000 | C11: Peso | D11: One-time consumer cost for the controller package only. This does NOT include the HVAC unit.
A12: Controller Installation & Setup Cost | B12: 0 | C12: Peso | D12: One-time installation, configuration, and commissioning cost for the controller.
A13: Smart Controller Annual Maintenance | B13: 1389.4 | C13: Peso/year | D13: Recurring consumer-side operating cost. Enter 0 if none.
A14: Additional HVAC Maintenance Savings (Optional) | B14: 0 | C14: Peso/year | D14: Optional avoided maintenance/service cost; keep 0 if not measured or quantified.
A15: Residual / Resale Value at End of Horizon | B15: 0 | C15: Peso | D15: Optional resale or residual value at the end of the analysis horizon.
... A18: Smart Controller Salvage Value | B18: 0 | C18: Peso | D18: Residual value at the end of the controller useful life for depreciation calculation.

Sheet Consumer Cash Flow
A1: Consumer Cash Flow: Existing HVAC vs Smart HVAC Controller Purchase
A3: Year | B3: Electricity Rate | C3: Manual HVAC kWh | D3: Smart HVAC kWh | E3: kWh Saved | F3: Manual Bill | G3: Smart Bill | H3: Recurring Smart Cost | I3: Net Annual Savings | J3: Discounted Savings | K3: Cumulative Net Cash Flow
A4: 0 | B4: 0 | C4: - | D4: - | E4: - | F4: - | G4: - | H4: - | I4: =-('Consumer Inputs'!B11+'Consumer Inputs'!B12+'Consumer Inputs'!B16) -> -26000 | J4: =I4 -> -26000 | K4: =J4 -> -26000
A5: 1 | B5: ='Consumer Inputs'!$B$5*(1+'Consumer Inputs'!$B$6)^(A5-1) -> 10.5049 | C5: ='Consumer Inputs'!$B$8*(1+'Consumer Inputs'!$B$9)^(A5-1) -> 2261.15 | D5: =C5*(1-'Consumer Inputs'!$B$10) -> 1796.7188 | E5: =C5-D5 -> 464.43117 | F5: =C5*B5 -> 23753.155 | G5: =D5*B5 -> 18874.352 | H5: ='Consumer Inputs'!$B$13 -> 1389.4 | I5: =(F5-G5)-H5+'Consumer Inputs'!$B$14 -> 3489.4029 | J5: =I5/(1+'Consumer Inputs'!$B$7)^A5 -> 2907.8358 | K5: =K4+I5 -> -22510.597
A6: 2 | B6: ='Consumer Inputs'!$B$5*(1+'Consumer Inputs'!$B$6)^(A6-1) -> 11.450341 | C6: ='Consumer Inputs'!$B$8*(1+'Consumer Inputs'!$B$9)^(A6-1) -> 2306.373 | D6: =C6*(1-'Consumer Inputs'!$B$10) -> 1832.6532 | E6: =C6-D6 -> 473.71979 | F6: =C6*B6 -> 26408.757 | G6: =D6*B6 -> 20984.504 | H6: ='Consumer Inputs'!$B$13 -> 1389.4 | I6: =(F6-G6)-H6+'Consumer Inputs'!$B$14 -> 4034.8531 | J6: =I6/(1+'Consumer Inputs'!$B$7)^A6 -> 2801.9813 | K6: =K5+I6 -> -18475.744
A7: 3 | B7: ='Consumer Inputs'!$B$5*(1+'Consumer Inputs'!$B$6)^(A7-1) -> 12.480872 | C7: ='Consumer Inputs'!$B$8*(1+'Consumer Inputs'!$B$9)^(A7-1) -> 2352.5005 | D7: =C7*(1-'Consumer Inputs'!$B$10) -> 1869.3063 | E7: =C7-D7 -> 483.19418 | F7: =C7*B7 -> 29361.256 | G7: =D7*B7 -> 23330.572 | H7: ='Consumer Inputs'!$B$13 -> 1389.4 | I7: =(F7-G7)-H7+'Consumer Inputs'!$B$14 -> 4641.2846 | J7: =I7/(1+'Consumer Inputs'!$B$7)^A7 -> 2685.9286 | K7: =K6+I7 -> -13834.459
A8: 4 | B8: ='Consumer Inputs'!$B$5*(1+'Consumer Inputs'!$B$6)^(A8-1) -> 13.60415 | C8: ='Consumer Inputs'!$B$8*(1+'Consumer Inputs'!$B$9)^(A8-1) -> 2399.5505 | D8: =C8*(1-'Consumer Inputs'!$B$10) -> 1906.6924 | E8: =C8-D8 -> 492.85807 | F8: =C8*B8 -> 32643.845 | G8: =D8*B8 -> 25938.93 | H8: ='Consumer Inputs'!$B$13 -> 1389.4 | I8: =(F8-G8)-H8+'Consumer Inputs'!$B$14 -> 5315.5152 | J8: =I8/(1+'Consumer Inputs'!$B$7)^A8 -> 2563.4236 | K8: =K7+I8 -> -8518.9442
A9: 5 | B9: ='Consumer Inputs'!$B$5*(1+'Consumer Inputs'!$B$6)^(A9-1) -> 14.828524 | C9: ='Consumer Inputs'!$B$8*(1+'Consumer Inputs'!$B$9)^(A9-1) -> 2447.5415 | D9: =C9*(1-'Consumer Inputs'!$B$10) -> 1944.8262 | E9: =C9-D9 -> 502.71523 | F9: =C9*B9 -> 36293.427 | G9: =D9*B9 -> 28838.902 | H9: ='Consumer Inputs'!$B$13 -> 1389.4 | I9: =(F9-G9)-H9+'Consumer Inputs'!$B$14 -> 6065.1247 | J9: =I9/(1+'Consumer Inputs'!$B$7)^A9 -> 2437.4376 | K9: =K8+I9 -> -2453.8195
A10: 6 | B10: ='Consumer Inputs'!$B$5*(1+'Consumer Inputs'!$B$6)^(A10-1) -> 16.163091 | C10: ='Consumer Inputs'!$B$8*(1+'Consumer Inputs'!$B$9)^(A10-1) -> 2496.4923 | D10: =C10*(1-'Consumer Inputs'!$B$10) -> 1983.7228 | E10: =C10-D10 -> 512.76953 | F10: =C10*B10 -> 40351.032 | G10: =D10*B10 -> 32063.091 | H10: ='Consumer Inputs'!$B$13 -> 1389.4 | I10: =(F10-G10)-H10+'Consumer Inputs'!$B$14 -> 6898.5405 | J10: =I10/(1+'Consumer Inputs'!$B$7)^A10 -> 2310.3073 | K10: =K9+I10 -> 4444.721
A11: 7 | B11: ='Consumer Inputs'!$B$5*(1+'Consumer Inputs'!$B$6)^(A11-1) -> 17.617769 | C11: ='Consumer Inputs'!$B$8*(1+'Consumer Inputs'!$B$9)^(A11-1) -> 2546.4222 | D11: =C11*(1-'Consumer Inputs'!$B$10) -> 2023.3972 | E11: =C11-D11 -> 523.02492 | F11: =C11*B11 -> 44862.277 | G11: =D11*B11 -> 35647.745 | H11: ='Consumer Inputs'!$B$13 -> 1389.4 | I11: =(F11-G11)-H11+'Consumer Inputs'!$B$14 -> 7825.1323 | J11: =I11/(1+'Consumer Inputs'!$B$7)^A11 -> 2183.8508 | K11: =K10+I11 -> 12269.853
A12: 8 | B12: ='Consumer Inputs'!$B$5*(1+'Consumer Inputs'!$B$6)^(A12-1) -> 19.203368 | C12: ='Consumer Inputs'!$B$8*(1+'Consumer Inputs'!$B$9)^(A12-1) -> 2597.3506 | D12: =C12*(1-'Consumer Inputs'!$B$10) -> 2063.8652 | E12: =C12-D12 -> 533.48542 | F12: =C12*B12 -> 49877.88 | G12: =D12*B12 -> 39633.163 | H12: ='Consumer Inputs'!$B$13 -> 1389.4 | I12: =(F12-G12)-H12+'Consumer Inputs'!$B$14 -> 8855.317 | J12: =I12/(1+'Consumer Inputs'!$B$7)^A12 -> 2059.4637 | K12: =K11+I12 -> 21125.17
A13: 9 | B13: ='Consumer Inputs'!$B$5*(1+'Consumer Inputs'!$B$6)^(A13-1) -> 20.931671 | C13: ='Consumer Inputs'!$B$8*(1+'Consumer Inputs'!$B$9)^(A13-1) -> 2649.2976 | D13: =C13*(1-'Consumer Inputs'!$B$10) -> 2105.1425 | E13: =C13-D13 -> 544.15513 | F13: =C13*B13 -> 55454.227 | G13: =D13*B13 -> 44064.15 | H13: ='Consumer Inputs'!$B$13 -> 1389.4 | I13: =(F13-G13)-H13+'Consumer Inputs'!$B$14 -> 10000.676 | J13: =I13/(1+'Consumer Inputs'!$B$7)^A13 -> 1938.1981 | K13: =K12+I13 -> 31125.847
A14: 10 | B14: ='Consumer Inputs'!$B$5*(1+'Consumer Inputs'!$B$6)^(A14-1) -> 22.815522 | C14: ='Consumer Inputs'!$B$8*(1+'Consumer Inputs'!$B$9)^(A14-1) -> 2702.2836 | D14: =C14*(1-'Consumer Inputs'!$B$10) -> 2147.2453 | E14: =C14-D14 -> 555.03823 | F14: =C14*B14 -> 61654.009 | G14: =D14*B14 -> 48990.522 | H14: ='Consumer Inputs'!$B$13 -> 1389.4 | I14: =(F14-G14)-H14+'Consumer Inputs'!$B$14 -> 11274.087 | J14: =I14/(1+'Consumer Inputs'!$B$7)^A14 -> 1820.828 | K14: =K13+I14 -> 42399.934
A15: 11 | B15: ='Consumer Inputs'!$B$5*(1+'Consumer Inputs'!$B$6)^(A15-1) -> 24.868919 | C15: ='Consumer Inputs'!$B$8*(1+'Consumer Inputs'!$B$9)^(A15-1) -> 2756.3292 | D15: =C15*(1-'Consumer Inputs'!$B$10) -> 2190.1902 | E15: =C15-D15 -> 566.139 | F15: =C15*B15 -> 68546.928 | G15: =D15*B15 -> 54467.663 | H15: ='Consumer Inputs'!$B$13 -> 1389.4 | I15: =(F15-G15)-H15+'Consumer Inputs'!$B$14 -> 12689.865 | J15: =I15/(1+'Consumer Inputs'!$B$7)^A15 -> 1707.9033 | K15: =K14+I15 -> 55089.798
A16: 12 | B16: ='Consumer Inputs'!$B$5*(1+'Consumer Inputs'!$B$6)^(A16-1) -> 27.107121 | C16: ='Consumer Inputs'!$B$8*(1+'Consumer Inputs'!$B$9)^(A16-1) -> 2811.4558 | D16: =C16*(1-'Consumer Inputs'!$B$10) -> 2233.994 | E16: =C16-D16 -> 577.46178 | F16: =C16*B16 -> 76210.474 | G16: =D16*B16 -> 60557.147 | H16: ='Consumer Inputs'!$B$13 -> 1389.4 | I16: =(F16-G16)-H16+'Consumer Inputs'!$B$14 -> 14263.927 | J16: =I16/(1+'Consumer Inputs'!$B$7)^A16 -> 1599.7943 | K16: =K15+I16 -> 69353.725

Sheet Consumer Scenarios
A1: Consumer Adoption Scenarios
A3: Scenario | B3: Controller Cost Factor | C3: Savings % | D3: Electricity Rate | E3: Year 1 Net Savings | F3: Total CAPEX | G3: Simple Payback | H3: 12-Year ROI
A4: Conservative | B4: 1.2 | C4: =C5 -> 0.205396 | D4: 9.5 | E4: =('Consumer Inputs'!B8*C4*D4)-'Consumer Inputs'!B13 -> 3022.6961 | F4: =('Consumer Inputs'!B11*B4)+'Consumer Inputs'!B12+'Consumer Inputs'!B16 -> 31200 | G4: =IF(E4>0,F4/E4,"Not recovered") -> 10.321911 | H4: =IF(F4>0,(E4*12+'Consumer Inputs'!B15-F4)/F4,0) -> 0.16257541
A5: Base | B5: 1 | C5: ='Consumer Inputs'!B10 -> 0.205396 | D5: ='Consumer Inputs'!B5 -> 10.5049 | E5: =('Consumer Inputs'!B8*C5*D5)-'Consumer Inputs'!B13 -> 3489.4029 | F5: =('Consumer Inputs'!B11*B5)+'Consumer Inputs'!B12+'Consumer Inputs'!B16 -> 26000 | G5: =IF(E5>0,F5/E5,"Not recovered") -> 7.4511314 | H5: =IF(F5>0,(E5*12+'Consumer Inputs'!B16-F5)/F5,0) -> 0.61049367
A6: Optimistic | B6: 0.9 | C6: =C5 -> 0.205396 | D6: 12 | E6: =('Consumer Inputs'!B8*C6*D6)-'Consumer Inputs'!B13 -> 4183.774 | F6: =('Consumer Inputs'!B11*B6)+'Consumer Inputs'!B12+'Consumer Inputs'!B16 -> 23400 | G6: =IF(E6>0,F6/E6,"Not recovered") -> 5.5930364 | H6: =IF(F6>0,(E6*12+'Consumer Inputs'!B17-F6)/F6,0) -> 1.1460379

Sheet Sensitivity Analysis
A1: Sensitivity Analysis: Payback Under Varying Electricity Rate and Savings
A3: Savings % \ Rate | B3: 8 | C3: 10 | D3: 12 | E3: 14 | F3: 16
A4: 0.02 | B4: =IF(('Consumer Inputs'!$B$8*$A4*B$3)-'Consumer Inputs'!$B$13+'Consumer Inputs'!$B$14>0,('Consumer Inputs'!$B$11+'Consumer Inputs'!$B$12+'Consumer Inputs'!$B$16)/(('Consumer Inputs'!$B$8*$A4*B$3)-'Consumer Inputs'!$B$13+'Consumer Inputs'!$B$14),"Not recovered") -> Not recovered | C4: =IF(('Consumer Inputs'!$B$8*$A4*C$3)-'Consumer Inputs'!$B$13+'Consumer Inputs'!$B$14>0,('Consumer Inputs'!$B$11+'Consumer Inputs'!$B$12+'Consumer Inputs'!$B$16)/(('Consumer Inputs'!$B$8*$A4*C$3)-'Consumer Inputs'!$B$13+'Consumer Inputs'!$B$14),"Not recovered") -> Not recovered | D4: =IF(('Consumer Inputs'!$B$8*$A4*D$3)-'Consumer Inputs'!$B$13+'Consumer Inputs'!$B$14>0,('Consumer Inputs'!$B$11+'Consumer Inputs'!$B$12+'Consumer Inputs'!$B$16)/(('Consumer Inputs'!$B$8*$A4*D$3)-'Consumer Inputs'!$B$13+'Consumer Inputs'!$B$14),"Not recovered") -> Not recovered | E4: =IF(('Consumer Inputs'!$B$8*$A4*E$3)-'Consumer Inputs'!$B$13+'Consumer Inputs'!$B$14>0,('Consumer Inputs'!$B$11+'Consumer Inputs'!$B$12+'Consumer Inputs'!$B$16)/(('Consumer Inputs'!$B$8*$A4*E$3)-'Consumer Inputs'!$B$13+'Consumer Inputs'!$B$14),"Not recovered") -> Not recovered | F4: =IF(('Consumer Inputs'!$B$8*$A4*F$3)-'Consumer Inputs'!$B$13+'Consumer Inputs'!$B$14>0,('Consumer Inputs'!$B$11+'Consumer Inputs'!$B$12+'Consumer Inputs'!$B$16)/(('Consumer Inputs'!$B$8*$A4*F$3)-'Consumer Inputs'!$B$13+'Consumer Inputs'!$B$14),"Not recovered") -> Not recovered
A5: 0.04 | B5: =IF(('Consumer Inputs'!$B$8*$A5*B$3)-'Consumer Inputs'!$B$13+'Consumer Inputs'!$B$14>0,('Consumer Inputs'!$B$11+'Consumer Inputs'!$B$12+'Consumer Inputs'!$B$16)/(('Consumer Inputs'!$B$8*$A5*B$3)-'Consumer Inputs'!$B$13+'Consumer Inputs'!$B$14),"Not recovered") -> Not recovered | C5: =IF(('Consumer Inputs'!$B$8*$A5*C$3)-'Consumer Inputs'!$B$13+'Consumer Inputs'!$B$14>0,('Consumer Inputs'!$B$11+'Consumer Inputs'!$B$12+'Consumer Inputs'!$B$16)/(('Consumer Inputs'!$B$8*$A5*C$3)-'Consumer Inputs'!$B$13+'Consumer Inputs'!$B$14),"Not recovered") -> Not recovered | D5: =IF(('Consumer Inputs'!$B$8*$A5*D$3)-'Consumer Inputs'!$B$13+'Consumer Inputs'!$B$14>0,('Consumer Inputs'!$B$11+'Consumer Inputs'!$B$12+'Consumer Inputs'!$B$16)/(('Consumer Inputs'!$B$8*$A5*D$3)-'Consumer Inputs'!$B$13+'Consumer Inputs'!$B$14),"Not recovered") -> Not recovered | E5: =IF(('Consumer Inputs'!$B$8*$A5*E$3)-'Consumer Inputs'!$B$13+'Consumer Inputs'!$B$14>0,('Consumer Inputs'!$B$11+'Consumer Inputs'!$B$12+'Consumer Inputs'!$B$16)/(('Consumer Inputs'!$B$8*$A5*E$3)-'Consumer Inputs'!$B$13+'Consumer Inputs'!$B$14),"Not recovered") -> Not recovered | F5: =IF(('Consumer Inputs'!$B$8*$A5*F$3)-'Consumer Inputs'!$B$13+'Consumer Inputs'!$B$14>0,('Consumer Inputs'!$B$11+'Consumer Inputs'!$B$12+'Consumer Inputs'!$B$16)/(('Consumer Inputs'!$B$8*$A5*F$3)-'Consumer Inputs'!$B$13+'Consumer Inputs'!$B$14),"Not recovered") -> 450.32562
A6: 0.06 | B6: =IF(('Consumer Inputs'!$B$8*$A6*B$3)-'Consumer Inputs'!$B$13+'Consumer Inputs'!$B$14>0,('Consumer Inputs'!$B$11+'Consumer Inputs'!$B$12+'Consumer Inputs'!$B$16)/(('Consumer Inputs'!$B$8*$A6*B$3)-'Consumer Inputs'!$B$13+'Consumer Inputs'!$B$14),"Not recovered") -> Not recovered | C6: =IF(('Consumer Inputs'!$B$8*$A6*C$3)-'Consumer Inputs'!$B$13+'Consumer Inputs'!$B$14>0,('Consumer Inputs'!$B$11+'Consumer Inputs'!$B$12+'Consumer Inputs'!$B$16)/(('Consumer Inputs'!$B$8*$A6*C$3)-'Consumer Inputs'!$B$13+'Consumer Inputs'!$B$14),"Not recovered") -> Not recovered | D6: =IF(('Consumer Inputs'!$B$8*$A6*D$3)-'Consumer Inputs'!$B$13+'Consumer Inputs'!$B$14>0,('Consumer Inputs'!$B$11+'Consumer Inputs'!$B$12+'Consumer Inputs'!$B$16)/(('Consumer Inputs'!$B$8*$A6*D$3)-'Consumer Inputs'!$B$13+'Consumer Inputs'!$B$14),"Not recovered") -> 108.9562 | E6: =IF(('Consumer Inputs'!$B$8*$A6*E$3)-'Consumer Inputs'!$B$13+'Consumer Inputs'!$B$14>0,('Consumer Inputs'!$B$11+'Consumer Inputs'!$B$12+'Consumer Inputs'!$B$16)/(('Consumer Inputs'!$B$8*$A6*E$3)-'Consumer Inputs'!$B$13+'Consumer Inputs'!$B$14),"Not recovered") -> 50.983791 | F6: =IF(('Consumer Inputs'!$B$8*$A6*F$3)-'Consumer Inputs'!$B$13+'Consumer Inputs'!$B$14>0,('Consumer Inputs'!$B$11+'Consumer Inputs'!$B$12+'Consumer Inputs'!$B$16)/(('Consumer Inputs'!$B$8*$A6*F$3)-'Consumer Inputs'!$B$13+'Consumer Inputs'!$B$14),"Not recovered") -> 33.2777
A7: 0.08 | B7: =IF(('Consumer Inputs'!$B$8*$A7*B$3)-'Consumer Inputs'!$B$13+'Consumer Inputs'!$B$14>0,('Consumer Inputs'!$B$11+'Consumer Inputs'!$B$12+'Consumer Inputs'!$B$16)/(('Consumer Inputs'!$B$8*$A7*B$3)-'Consumer Inputs'!$B$13+'Consumer Inputs'!$B$14),"Not recovered") -> 450.32562 | C7: =IF(('Consumer Inputs'!$B$8*$A7*C$3)-'Consumer Inputs'!$B$13+'Consumer Inputs'!$B$14>0,('Consumer Inputs'!$B$11+'Consumer Inputs'!$B$12+'Consumer Inputs'!$B$16)/(('Consumer Inputs'!$B$8*$A7*C$3)-'Consumer Inputs'!$B$13+'Consumer Inputs'!$B$14),"Not recovered") -> 61.975591 | D7: =IF(('Consumer Inputs'!$B$8*$A7*D$3)-'Consumer Inputs'!$B$13+'Consumer Inputs'!$B$14>0,('Consumer Inputs'!$B$11+'Consumer Inputs'!$B$12+'Consumer Inputs'!$B$16)/(('Consumer Inputs'!$B$8*$A7*D$3)-'Consumer Inputs'!$B$13+'Consumer Inputs'!$B$14),"Not recovered") -> 33.2777 | E7: =IF(('Consumer Inputs'!$B$8*$A7*E$3)-'Consumer Inputs'!$B$13+'Consumer Inputs'!$B$14>0,('Consumer Inputs'!$B$11+'Consumer Inputs'!$B$12+'Consumer Inputs'!$B$16)/(('Consumer Inputs'!$B$8*$A7*E$3)-'Consumer Inputs'!$B$13+'Consumer Inputs'!$B$14),"Not recovered") -> 22.745405 | F7: =IF(('Consumer Inputs'!$B$8*$A7*F$3)-'Consumer Inputs'!$B$13+'Consumer Inputs'!$B$14>0,('Consumer Inputs'!$B$11+'Consumer Inputs'!$B$12+'Consumer Inputs'!$B$16)/(('Consumer Inputs'!$B$8*$A7*F$3)-'Consumer Inputs'!$B$13+'Consumer Inputs'!$B$14),"Not recovered") -> 17.277217
A8: 0.1 | B8: =IF(('Consumer Inputs'!$B$8*$A8*B$3)-'Consumer Inputs'!$B$13+'Consumer Inputs'!$B$14>0,('Consumer Inputs'!$B$11+'Consumer Inputs'!$B$12+'Consumer Inputs'!$B$16)/(('Consumer Inputs'!$B$8*$A8*B$3)-'Consumer Inputs'!$B$13+'Consumer Inputs'!$B$14),"Not recovered") -> 61.975591 | C8: =IF(('Consumer Inputs'!$B$8*$A8*C$3)-'Consumer Inputs'!$B$13+'Consumer Inputs'!$B$14>0,('Consumer Inputs'!$B$11+'Consumer Inputs'!$B$12+'Consumer Inputs'!$B$16)/(('Consumer Inputs'!$B$8*$A8*C$3)-'Consumer Inputs'!$B$13+'Consumer Inputs'!$B$14),"Not recovered") -> 29.825065 | D8: =IF(('Consumer Inputs'!$B$8*$A8*D$3)-'Consumer Inputs'!$B$13+'Consumer Inputs'!$B$14>0,('Consumer Inputs'!$B$11+'Consumer Inputs'!$B$12+'Consumer Inputs'!$B$16)/(('Consumer Inputs'!$B$8*$A8*D$3)-'Consumer Inputs'!$B$13+'Consumer Inputs'!$B$14),"Not recovered") -> 19.637759 | E8: =IF(('Consumer Inputs'!$B$8*$A8*E$3)-'Consumer Inputs'!$B$13+'Consumer Inputs'!$B$14>0,('Consumer Inputs'!$B$11+'Consumer Inputs'!$B$12+'Consumer Inputs'!$B$16)/(('Consumer Inputs'!$B$8*$A8*E$3)-'Consumer Inputs'!$B$13+'Consumer Inputs'!$B$14),"Not recovered") -> 14.637909 | F8: =IF(('Consumer Inputs'!$B$8*$A8*F$3)-'Consumer Inputs'!$B$13+'Consumer Inputs'!$B$14>0,('Consumer Inputs'!$B$11+'Consumer Inputs'!$B$12+'Consumer Inputs'!$B$16)/(('Consumer Inputs'!$B$8*$A8*F$3)-'Consumer Inputs'!$B$13+'Consumer Inputs'!$B$14),"Not recovered") -> 11.667355
A9: 0.12 | B9: =IF(('Consumer Inputs'!$B$8*$A9*B$3)-'Consumer Inputs'!$B$13+'Consumer Inputs'!$B$14>0,('Consumer Inputs'!$B$11+'Consumer Inputs'!$B$12+'Consumer Inputs'!$B$16)/(('Consumer Inputs'!$B$8*$A9*B$3)-'Consumer Inputs'!$B$13+'Consumer Inputs'!$B$14),"Not recovered") -> 33.2777 | C9: =IF(('Consumer Inputs'!$B$8*$A9*C$3)-'Consumer Inputs'!$B$13+'Consumer Inputs'!$B$14>0,('Consumer Inputs'!$B$11+'Consumer Inputs'!$B$12+'Consumer Inputs'!$B$16)/(('Consumer Inputs'!$B$8*$A9*C$3)-'Consumer Inputs'!$B$13+'Consumer Inputs'!$B$14),"Not recovered") -> 19.637759 | D9: =IF(('Consumer Inputs'!$B$8*$A9*D$3)-'Consumer Inputs'!$B$13+'Consumer Inputs'!$B$14>0,('Consumer Inputs'!$B$11+'Consumer Inputs'!$B$12+'Consumer Inputs'!$B$16)/(('Consumer Inputs'!$B$8*$A9*D$3)-'Consumer Inputs'!$B$13+'Consumer Inputs'!$B$14),"Not recovered") -> 13.928651 | E9: =IF(('Consumer Inputs'!$B$8*$A9*E$3)-'Consumer Inputs'!$B$13+'Consumer Inputs'!$B$14>0,('Consumer Inputs'!$B$11+'Consumer Inputs'!$B$12+'Consumer Inputs'!$B$16)/(('Consumer Inputs'!$B$8*$A9*E$3)-'Consumer Inputs'!$B$13+'Consumer Inputs'!$B$14),"Not recovered") -> 10.791373 | F9: =IF(('Consumer Inputs'!$B$8*$A9*F$3)-'Consumer Inputs'!$B$13+'Consumer Inputs'!$B$14>0,('Consumer Inputs'!$B$11+'Consumer Inputs'!$B$12+'Consumer Inputs'!$B$16)/(('Consumer Inputs'!$B$8*$A9*F$3)-'Consumer Inputs'!$B$13+'Consumer Inputs'!$B$14),"Not recovered") -> 8.8075642

Sheet Depreciation Schedule
A1: Straight-Line Depreciation of Smart HVAC Controller Package
A3: Year | B3: Annual Depreciation | C3: Accumulated Depreciation | D3: Book Value | E3: Note
A4: 0 | B4: =0 -> 0 | C4: =0 -> 0 | D4: ='Consumer Inputs'!B11+'Consumer Inputs'!B12 -> 26000 | E4: Initial book value of controller asset.
A5: 1 | B5: =IF(A5<='Consumer Inputs'!$B$17,(('Consumer Inputs'!$B$11+'Consumer Inputs'!$B$12)-'Consumer Inputs'!$B$18)/'Consumer Inputs'!$B$17,0) -> 2166.6667 | C5: =MIN(('Consumer Inputs'!$B$11+'Consumer Inputs'!$B$12)-'Consumer Inputs'!$B$18,SUM($B$5:B5)) -> 2166.6667 | D5: =MAX('Consumer Inputs'!$B$18,('Consumer Inputs'!$B$11+'Consumer Inputs'!$B$12)-C5) -> 23833.333 | E5: Depreciation is accounting-based and is not deducted from cash savings.
A6: 2 | B6: =IF(A6<='Consumer Inputs'!$B$17,(('Consumer Inputs'!$B$11+'Consumer Inputs'!$B$12)-'Consumer Inputs'!$B$18)/'Consumer Inputs'!$B$17,0) -> 2166.6667 | C6: =MIN(('Consumer Inputs'!$B$11+'Consumer Inputs'!$B$12)-'Consumer Inputs'!$B$18,SUM($B$5:B6)) -> 4333.3333 | D6: =MAX('Consumer Inputs'!$B$18,('Consumer Inputs'!$B$11+'Consumer Inputs'!$B$12)-C6) -> 21666.667 | E6: Depreciation is accounting-based and is not deducted from cash savings.
A7: 3 | B7: =IF(A7<='Consumer Inputs'!$B$17,(('Consumer Inputs'!$B$11+'Consumer Inputs'!$B$12)-'Consumer Inputs'!$B$18)/'Consumer Inputs'!$B$17,0) -> 2166.6667 | C7: =MIN(('Consumer Inputs'!$B$11+'Consumer Inputs'!$B$12)-'Consumer Inputs'!$B$18,SUM($B$5:B7)) -> 6500 | D7: =MAX('Consumer Inputs'!$B$18,('Consumer Inputs'!$B$11+'Consumer Inputs'!$B$12)-C7) -> 19500 | E7: Depreciation is accounting-based and is not deducted from cash savings.
A8: 4 | B8: =IF(A8<='Consumer Inputs'!$B$17,(('Consumer Inputs'!$B$11+'Consumer Inputs'!$B$12)-'Consumer Inputs'!$B$18)/'Consumer Inputs'!$B$17,0) -> 2166.6667 | C8: =MIN(('Consumer Inputs'!$B$11+'Consumer Inputs'!$B$12)-'Consumer Inputs'!$B$18,SUM($B$5:B8)) -> 8666.6667 | D8: =MAX('Consumer Inputs'!$B$18,('Consumer Inputs'!$B$11+'Consumer Inputs'!$B$12)-C8) -> 17333.333 | E8: Depreciation is accounting-based and is not deducted from cash savings.
A9: 5 | B9: =IF(A9<='Consumer Inputs'!$B$17,(('Consumer Inputs'!$B$11+'Consumer Inputs'!$B$12)-'Consumer Inputs'!$B$18)/'Consumer Inputs'!$B$17,0) -> 2166.6667 | C9: =MIN(('Consumer Inputs'!$B$11+'Consumer Inputs'!$B$12)-'Consumer Inputs'!$B$18,SUM($B$5:B9)) -> 10833.333 | D9: =MAX('Consumer Inputs'!$B$18,('Consumer Inputs'!$B$11+'Consumer Inputs'!$B$12)-C9) -> 15166.667 | E9: Depreciation is accounting-based and is not deducted from cash savings.
A10: 6 | B10: =IF(A10<='Consumer Inputs'!$B$17,(('Consumer Inputs'!$B$11+'Consumer Inputs'!$B$12)-'Consumer Inputs'!$B$18)/'Consumer Inputs'!$B$17,0) -> 2166.6667 | C10: =MIN(('Consumer Inputs'!$B$11+'Consumer Inputs'!$B$12)-'Consumer Inputs'!$B$18,SUM($B$5:B10)) -> 13000 | D10: =MAX('Consumer Inputs'!$B$18,('Consumer Inputs'!$B$11+'Consumer Inputs'!$B$12)-C10) -> 13000 | E10: Depreciation is accounting-based and is not deducted from cash savings.
A11: 7 | B11: =IF(A11<='Consumer Inputs'!$B$17,(('Consumer Inputs'!$B$11+'Consumer Inputs'!$B$12)-'Consumer Inputs'!$B$18)/'Consumer Inputs'!$B$17,0) -> 2166.6667 | C11: =MIN(('Consumer Inputs'!$B$11+'Consumer Inputs'!$B$12)-'Consumer Inputs'!$B$18,SUM($B$5:B11)) -> 15166.667 | D11: =MAX('Consumer Inputs'!$B$18,('Consumer Inputs'!$B$11+'Consumer Inputs'!$B$12)-C11) -> 10833.333 | E11: Depreciation is accounting-based and is not deducted from cash savings.
A12: 8 | B12: =IF(A12<='Consumer Inputs'!$B$17,(('Consumer Inputs'!$B$11+'Consumer Inputs'!$B$12)-'Consumer Inputs'!$B$18)/'Consumer Inputs'!$B$17,0) -> 2166.6667 | C12: =MIN(('Consumer Inputs'!$B$11+'Consumer Inputs'!$B$12)-'Consumer Inputs'!$B$18,SUM($B$5:B12)) -> 17333.333 | D12: =MAX('Consumer Inputs'!$B$18,('Consumer Inputs'!$B$11+'Consumer Inputs'!$B$12)-C12) -> 8666.6667 | E12: Depreciation is accounting-based and is not deducted from cash savings.
A13: 9 | B13: =IF(A13<='Consumer Inputs'!$B$17,(('Consumer Inputs'!$B$11+'Consumer Inputs'!$B$12)-'Consumer Inputs'!$B$18)/'Consumer Inputs'!$B$17,0) -> 2166.6667 | C13: =MIN(('Consumer Inputs'!$B$11+'Consumer Inputs'!$B$12)-'Consumer Inputs'!$B$18,SUM($B$5:B13)) -> 19500 | D13: =MAX('Consumer Inputs'!$B$18,('Consumer Inputs'!$B$11+'Consumer Inputs'!$B$12)-C13) -> 6500 | E13: Depreciation is accounting-based and is not deducted from cash savings.
A14: 10 | B14: =IF(A14<='Consumer Inputs'!$B$17,(('Consumer Inputs'!$B$11+'Consumer Inputs'!$B$12)-'Consumer Inputs'!$B$18)/'Consumer Inputs'!$B$17,0) -> 2166.6667 | C14: =MIN(('Consumer Inputs'!$B$11+'Consumer Inputs'!$B$12)-'Consumer Inputs'!$B$18,SUM($B$5:B14)) -> 21666.667 | D14: =MAX('Consumer Inputs'!$B$18,('Consumer Inputs'!$B$11+'Consumer Inputs'!$B$12)-C14) -> 4333.3333 | E14: Depreciation is accounting-based and is not deducted from cash savings.
A15: 11 | B15: =IF(A15<='Consumer Inputs'!$B$17,(('Consumer Inputs'!$B$11+'Consumer Inputs'!$B$12)-'Consumer Inputs'!$B$18)/'Consumer Inputs'!$B$17,0) -> 2166.6667 | C15: =MIN(('Consumer Inputs'!$B$11+'Consumer Inputs'!$B$12)-'Consumer Inputs'!$B$18,SUM($B$5:B15)) -> 23833.333 | D15: =MAX('Consumer Inputs'!$B$18,('Consumer Inputs'!$B$11+'Consumer Inputs'!$B$12)-C15) -> 2166.6667 | E15: Depreciation is accounting-based and is not deducted from cash savings.
A16: 12 | B16: =IF(A16<='Consumer Inputs'!$B$17,(('Consumer Inputs'!$B$11+'Consumer Inputs'!$B$12)-'Consumer Inputs'!$B$18)/'Consumer Inputs'!$B$17,0) -> 2166.6667 | C16: =MIN(('Consumer Inputs'!$B$11+'Consumer Inputs'!$B$12)-'Consumer Inputs'!$B$18,SUM($B$5:B16)) -> 26000 | D16: =MAX('Consumer Inputs'!$B$18,('Consumer Inputs'!$B$11+'Consumer Inputs'!$B$12)-C16) -> 0 | E16: Depreciation is accounting-based and is not deducted from cash savings.

Sheet Methodology Notes
A1: Smart HVAC Controller Consumer-Side Techno-Economic Methodology
A3: Scope | B3: This workbook evaluates the consumer's economic benefit from purchasing the Smart HVAC controller package. It does not include the cost of buying a new HVAC unit, because the controller is installed on an existing HVAC system.
A4: CAPEX | B4: Consumer CAPEX includes the controller package cost, controller installation/setup cost, and optional financing cost. It excludes producer-side costs such as R&D, manufacturing overhead, marketing, and salaries.
A5: OPEX | B5: Consumer OPEX includes recurring costs paid by the consumer after purchase, such as maintenance, cloud service, subscription, software support, or periodic calibration. If no recurring cost exists, enter 0.
A6: Baseline Energy | B6: Existing HVAC Annual Energy Consumption is the Year 1 energy use of the current/manual HVAC operation before installing the controller. This should come from measured data, a calibrated simulation, or a validated digital twin.
A7: Variable kWh | B7: Manual HVAC kWh is allowed to vary annually using the Annual HVAC Energy Consumption Variation input. This accounts for changes in weather, occupancy, operating hours, and equipment aging.
A8: Smart HVAC kWh | B8: Smart HVAC kWh is calculated by applying the measured controller savings percentage to each year's projected manual HVAC kWh. The HVAC unit remains the same; only the control strategy changes.
A9: Net Annual Savings | B9: Net Annual Savings = Manual Bill − Smart Bill − Smart Controller OPEX + Additional Maintenance Savings. This is the cash benefit used for payback and ROI.
A10: Payback | B10: Simple Payback = Total Consumer CAPEX / Year 1 Net Annual Savings. The cash-flow sheet also shows the year when cumulative net cash flow becomes positive.
A11: Discounted Payback | B11: Discounted savings apply the optional discount rate to reflect the time value of money. This is shown as a supporting metric; simple payback and ROI are still reported for consumer readability.
A12: ROI | B12: ROI = (Cumulative Net Savings + Residual Value − Initial CAPEX) / Initial CAPEX. It is shown for 3-year, 5-year, and 10-year consumer ownership periods.
A13: Depreciation | B13: Straight-line depreciation is included only as a supporting accounting indicator for the controller asset. It is not subtracted from cash savings because depreciation is not an actual cash outflow.
A14: Yellow Cells | B14: Yellow cells in the Consumer Inputs sheet are editable assumptions. Formula cells in other sheets should generally not be modified.
A15: Defense Note | B15: The economic story is: the consumer already has an HVAC unit, buys only the smart controller, pays any recurring controller OPEX, and receives savings from reduced HVAC electricity consumption.
